rll/__init__.py
rll/convert.py
rll/plotting.py
rll/seer.py
rll/version.py
tests/test_convert.py
tests/test_plotting.py
rll-0.1.6.dist-info/LICENSE
rll-0.1.6.dist-info/METADATA
rll-0.1.6.dist-info/WHEEL
rll-0.1.6.dist-info/top_level.txt
rll-0.1.6.dist-info/RECORD
