Metadata-Version: 2.1
Name: rll
Version: 0.1.6
Summary: Collection of different methods frequently used in the reiterlab across projects.
Home-page: https://github.com/reiterlab/rll
Author: Johannes Reiter
Author-email: johannes.reiter@stanford.edu
License: GNUv3
Platform: UNKNOWN
Classifier: Programming Language :: Python :: 3.6
Provides-Extra: plotting
